setup.py
kiji_bento_cluster.egg-info/PKG-INFO
kiji_bento_cluster.egg-info/SOURCES.txt
kiji_bento_cluster.egg-info/dependency_links.txt
kiji_bento_cluster.egg-info/requires.txt
kiji_bento_cluster.egg-info/top_level.txt
src/main/python/bento/__init__.py
src/main/python/bento/bento-env-template.sh
src/main/python/bento/bento-sudoers-template
src/main/python/bento/cli.py
src/main/python/bento/cluster.py
src/main/python/bento/core-site-template.xml
src/main/python/bento/hbase-site-template.xml
src/main/python/bento/hdfs-site-template.xml
src/main/python/bento/mapred-site-template.xml
src/main/python/bento/yarn-site-template.xml
src/main/scripts/add-bento-route
src/main/scripts/bento
src/main/scripts/create-hadoop-user
src/main/scripts/update-etc-hosts
src/main/scripts/update-user-hosts