Metadata-Version: 1.0
Name: kiji-bento-cluster
Version: 2.0.9
Summary: CDH and Datastax Enterprise docker single-node development cluster.
Home-page: http://www.kiji.org/
Author: WibiData
Author-email: user@kiji.org
License: Apache License 2.0
Keywords: bento,kijiproject,kiji,hadoop,hbase,cdh,cassandra
Platform: UNKNOWN
